jupyter_analysis_tools/__init__.py
jupyter_analysis_tools/analysis.py
jupyter_analysis_tools/binning.py
jupyter_analysis_tools/datalocations.py
jupyter_analysis_tools/datastore.py
jupyter_analysis_tools/distrib.py
jupyter_analysis_tools/git.py
jupyter_analysis_tools/plotting.py
jupyter_analysis_tools/readdata.py
jupyter_analysis_tools/ssfz2json.py
jupyter_analysis_tools/ssfz_compare.py
jupyter_analysis_tools/utils.py
jupyter_analysis_tools/widgets.py
jupyter_analysis_tools-1.7.2.dist-info/licenses/AUTHORS.rst
jupyter_analysis_tools-1.7.2.dist-info/licenses/LICENSE
jupyter_analysis_tools-1.7.2.dist-info/METADATA
jupyter_analysis_tools-1.7.2.dist-info/WHEEL
jupyter_analysis_tools-1.7.2.dist-info/entry_points.txt
jupyter_analysis_tools-1.7.2.dist-info/top_level.txt
jupyter_analysis_tools-1.7.2.dist-info/RECORD
