Metadata-Version: 2.4
Name: jupyter-analysis-tools
Version: 1.7.2
Summary: Yet another Python library with helpers and utilities for data analysis and processing.
Author-email: Ingo Breßler <ingo.bressler@bam.de>, "Brian R. Pauw" <brian.pauw@bam.de>
License-Expression: MIT
Project-URL: homepage, https://BAMresearch.github.io/jupyter-analysis-tools
Project-URL: documentation, https://BAMresearch.github.io/jupyter-analysis-tools
Project-URL: repository, https://github.com/BAMresearch/jupyter-analysis-tools
Project-URL: changelog, https://BAMresearch.github.io/jupyter-analysis-tools/changelog.html
Classifier: Development Status :: 4 - Beta
Classifier: Operating System :: Unix
Classifier: Operating System :: POSIX
Classifier: Operating System :: MacOS
Classifier: Operating System :: Microsoft :: Windows
Classifier: Programming Language :: Python
Classifier: Programming Language :: Python :: 3
Classifier: Programming Language :: Python :: 3 :: Only
Classifier: Programming Language :: Python :: 3.11
Classifier: Programming Language :: Python :: 3.12
Classifier: Programming Language :: Python :: 3.13
Classifier: Programming Language :: Python :: Implementation :: CPython
Classifier: Framework :: Jupyter :: JupyterLab
Classifier: Topic :: Utilities
Classifier: Topic :: Scientific/Engineering
Classifier: Intended Audience :: Developers
Classifier: Intended Audience :: Science/Research
License-File: LICENSE
License-File: AUTHORS.rst
Requires-Dist: numpy
Requires-Dist: scipy
Requires-Dist: pandas
Requires-Dist: matplotlib
Requires-Dist: ipywidgets
Requires-Dist: pybis
Dynamic: license-file
